Metadata-Version: 1.1
Name: mongo-join-rs
Version: 0.3
Summary: Small utility to join/leave MongoDB replicaset
Home-page: https://github.com/kedare/mongo-join-rs
Author: kedare
Author-email: mathieu.poussin@netyxia.net
License: UNKNOWN
Keywords: mongodb mongo autoscaling automation
Platform: UNKNOWN
Classifier: Operating System :: OS Independent
Classifier: Intended Audience :: Developers
Classifier: Programming Language :: Python :: 3
Classifier: Programming Language :: Python :: 3.5
